proplate/__init__.py
proplate/cli.py
proplate/clipboard.py
proplate/selector.py
proplate/template.py
proplate-0.3.0.dist-info/METADATA
proplate-0.3.0.dist-info/WHEEL
proplate-0.3.0.dist-info/entry_points.txt
proplate-0.3.0.dist-info/RECORD
