Metadata-Version: 2.4
Name: proplate
Version: 0.3.0
Summary: A CLI tool for managing and using prompt templates with placeholder injection.
Author-email: Elior Cohen <elior.cohen.p@gmail.com>
Requires-Python: >=3.12
Requires-Dist: pyperclip>=1.11.0
Requires-Dist: pyyaml>=6.0.3
Requires-Dist: questionary>=2.1.1
Requires-Dist: rich>=14.1.0
Requires-Dist: typer>=0.19.2
